{
  "dataVersion": 1,
  "skills": [
    {
      "id": "warrior_berserk",
      "displayName": "skill.rpgmod.warrior_berserk",
      "requiredAdvancementId": "warrior_first",
      "requiredLevel": 30,
      "minStr": 20,
      "minAgi": 0,
      "minWis": 0,
      "minLuk": 0,
      "resourceCost": 25.0,
      "cooldownSeconds": 30.0,
      "durationTicks": 120,
      "bonusAttackMultiplier": 1.35,
      "bonusArmor": 2.0,
      "bonusCritChance": 3.0,
      "bonusCritDamage": 10.0
    },
    {
      "id": "rogue_focus_burst",
      "displayName": "skill.rpgmod.rogue_focus_burst",
      "requiredAdvancementId": "rogue_first",
      "requiredLevel": 30,
      "minStr": 0,
      "minAgi": 20,
      "minWis": 0,
      "minLuk": 10,
      "resourceCost": 20.0,
      "cooldownSeconds": 24.0,
      "durationTicks": 100,
      "bonusAttackMultiplier": 1.28,
      "bonusArmor": 1.0,
      "bonusCritChance": 6.0,
      "bonusCritDamage": 15.0
    },
    {
      "id": "mage_arcane_barrier",
      "displayName": "skill.rpgmod.mage_arcane_barrier",
      "requiredAdvancementId": "mage_first",
      "requiredLevel": 30,
      "minStr": 0,
      "minAgi": 0,
      "minWis": 20,
      "minLuk": 0,
      "resourceCost": 30.0,
      "cooldownSeconds": 36.0,
      "durationTicks": 140,
      "bonusAttackMultiplier": 1.1,
      "bonusArmor": 6.0,
      "bonusCritChance": 0.0,
      "bonusCritDamage": 0.0
    },
    {
      "id": "archer_deadeye",
      "displayName": "skill.rpgmod.archer_deadeye",
      "requiredAdvancementId": "archer_first",
      "requiredLevel": 30,
      "minStr": 0,
      "minAgi": 15,
      "minWis": 0,
      "minLuk": 15,
      "resourceCost": 18.0,
      "cooldownSeconds": 20.0,
      "durationTicks": 80,
      "bonusAttackMultiplier": 1.22,
      "bonusArmor": 0.0,
      "bonusCritChance": 8.0,
      "bonusCritDamage": 20.0
    },
    {
      "id": "warrior_last_stand",
      "displayName": "skill.rpgmod.warrior_last_stand",
      "requiredAdvancementId": "warrior_second_warrior",
      "requiredLevel": 70,
      "minStr": 40,
      "minAgi": 0,
      "minWis": 0,
      "minLuk": 10,
      "resourceCost": 45.0,
      "cooldownSeconds": 45.0,
      "durationTicks": 120,
      "bonusAttackMultiplier": 1.4,
      "bonusArmor": 8.0,
      "bonusCritChance": 0.0,
      "bonusCritDamage": 15.0
    },
    {
      "id": "swordsman_blade_dance",
      "displayName": "skill.rpgmod.swordsman_blade_dance",
      "requiredAdvancementId": "warrior_second_swordsman",
      "requiredLevel": 70,
      "minStr": 30,
      "minAgi": 25,
      "minWis": 0,
      "minLuk": 15,
      "resourceCost": 35.0,
      "cooldownSeconds": 28.0,
      "durationTicks": 100,
      "bonusAttackMultiplier": 1.36,
      "bonusArmor": 2.0,
      "bonusCritChance": 10.0,
      "bonusCritDamage": 18.0
    },
    {
      "id": "assassin_shadow_execution",
      "displayName": "skill.rpgmod.assassin_shadow_execution",
      "requiredAdvancementId": "rogue_second_assassin",
      "requiredLevel": 70,
      "minStr": 10,
      "minAgi": 35,
      "minWis": 0,
      "minLuk": 30,
      "resourceCost": 30.0,
      "cooldownSeconds": 24.0,
      "durationTicks": 80,
      "bonusAttackMultiplier": 1.45,
      "bonusArmor": 0.0,
      "bonusCritChance": 14.0,
      "bonusCritDamage": 30.0
    },
    {
      "id": "pyromancer_overheat",
      "displayName": "skill.rpgmod.pyromancer_overheat",
      "requiredAdvancementId": "mage_second_pyromancer",
      "requiredLevel": 70,
      "minStr": 0,
      "minAgi": 0,
      "minWis": 40,
      "minLuk": 10,
      "resourceCost": 45.0,
      "cooldownSeconds": 34.0,
      "durationTicks": 120,
      "bonusAttackMultiplier": 1.42,
      "bonusArmor": 0.0,
      "bonusCritChance": 8.0,
      "bonusCritDamage": 22.0
    },
    {
      "id": "cryomancer_frozen_core",
      "displayName": "skill.rpgmod.cryomancer_frozen_core",
      "requiredAdvancementId": "mage_second_cryomancer",
      "requiredLevel": 70,
      "minStr": 0,
      "minAgi": 0,
      "minWis": 38,
      "minLuk": 14,
      "resourceCost": 42.0,
      "cooldownSeconds": 34.0,
      "durationTicks": 140,
      "bonusAttackMultiplier": 1.26,
      "bonusArmor": 10.0,
      "bonusCritChance": 0.0,
      "bonusCritDamage": 12.0
    },
    {
      "id": "shadowcaster_void_mark",
      "displayName": "skill.rpgmod.shadowcaster_void_mark",
      "requiredAdvancementId": "mage_second_shadowcaster",
      "requiredLevel": 70,
      "minStr": 0,
      "minAgi": 0,
      "minWis": 36,
      "minLuk": 24,
      "resourceCost": 40.0,
      "cooldownSeconds": 30.0,
      "durationTicks": 100,
      "bonusAttackMultiplier": 1.34,
      "bonusArmor": 2.0,
      "bonusCritChance": 12.0,
      "bonusCritDamage": 24.0
    },
    {
      "id": "lightcaster_sanctuary",
      "displayName": "skill.rpgmod.lightcaster_sanctuary",
      "requiredAdvancementId": "mage_second_lightcaster",
      "requiredLevel": 70,
      "minStr": 0,
      "minAgi": 0,
      "minWis": 36,
      "minLuk": 18,
      "resourceCost": 42.0,
      "cooldownSeconds": 38.0,
      "durationTicks": 140,
      "bonusAttackMultiplier": 1.2,
      "bonusArmor": 12.0,
      "bonusCritChance": 0.0,
      "bonusCritDamage": 8.0
    },
    {
      "id": "sniper_killing_zone",
      "displayName": "skill.rpgmod.sniper_killing_zone",
      "requiredAdvancementId": "archer_second_sniper",
      "requiredLevel": 70,
      "minStr": 8,
      "minAgi": 35,
      "minWis": 0,
      "minLuk": 28,
      "resourceCost": 30.0,
      "cooldownSeconds": 22.0,
      "durationTicks": 80,
      "bonusAttackMultiplier": 1.44,
      "bonusArmor": 0.0,
      "bonusCritChance": 14.0,
      "bonusCritDamage": 28.0
    }
  ]
}
